Metadata-Version: 1.1
Name: wild
Version: 1.0.1
Summary: Wildebeest CLI for Data Catalog at https://www.n3ncloud.co.kr
Home-page: https://github.com/n3nc/wild-cli
Author: N3NCLOUD
Author-email: mgkim@n3ncloud.co.kr
License: Apache 2.0
Download-URL: https://github.com/n3nc/wild-cli/archive/v_10.tar.gz
Keywords: Wildebeest,wild,API,CLI,N3NCLOUD
Platform: UNKNOWN
Classifier: Development Status :: 4 - Beta
Classifier: License :: OSI Approved :: Apache Software License
Classifier: Environment :: Console
Classifier: Programming Language :: Python :: 3
Classifier: Programming Language :: Python :: 3.4
Classifier: Programming Language :: Python :: 3.5
Classifier: Programming Language :: Python :: 3.6
